pennylane_qchem/__init__.py
pennylane_qchem/_version.py
pennylane_qchem/qchem/__init__.py
pennylane_qchem/qchem/obs.py
pennylane_qchem/qchem/openfermion.py
pennylane_qchem/qchem/structure.py
tests/__init__.py
tests/conftest.py
tests/test_active_space.py
tests/test_convert_observable.py
tests/test_decompose.py
tests/test_deriv_hamilt.py
tests/test_dipole.py
tests/test_excitations.py
tests/test_excitations_to_wires.py
tests/test_hf_state.py
tests/test_meanfield.py
tests/test_molecular_hamiltonian.py
tests/test_observable.py
tests/test_one_particle.py
tests/test_particle_number_obs.py
tests/test_read_structure.py
tests/test_s2_obs.py
tests/test_sz_obs.py
tests/test_two_particle.py
PennyLane_Qchem-0.23.0.dist-info/LICENSE
PennyLane_Qchem-0.23.0.dist-info/METADATA
PennyLane_Qchem-0.23.0.dist-info/WHEEL
PennyLane_Qchem-0.23.0.dist-info/entry_points.txt
PennyLane_Qchem-0.23.0.dist-info/top_level.txt
PennyLane_Qchem-0.23.0.dist-info/RECORD
